asynctg/__init__.py
asynctg/api.py
asynctg/client.py
asynctg/constants.py
asynctg/logger.py
asynctg/types.py
asynctg/update_manager.py
asynctg/utils.py
asynctg-1.0.6.dist-info/LICENSE
asynctg-1.0.6.dist-info/METADATA
asynctg-1.0.6.dist-info/WHEEL
asynctg-1.0.6.dist-info/top_level.txt
asynctg-1.0.6.dist-info/RECORD
